[
  {
    "id": 3001000,
    "text": null
  },
  {
    "id": 3001001,
    "text": null
  },
  {
    "id": 3001002,
    "text": null
  },
  {
    "id": 3001003,
    "text": null
  },
  {
    "id": 3001004,
    "text": null
  },
  {
    "id": 3001005,
    "text": null
  },
  {
    "id": 3001006,
    "text": null
  },
  {
    "id": 3001007,
    "text": null
  },
  {
    "id": 3001008,
    "text": null
  },
  {
    "id": 3001009,
    "text": null
  },
  {
    "id": 3001010,
    "text": null
  },
  {
    "id": 3001011,
    "text": null
  },
  {
    "id": 3001012,
    "text": null
  },
  {
    "id": 3001013,
    "text": null
  },
  {
    "id": 3001014,
    "text": null
  },
  {
    "id": 3001015,
    "text": null
  },
  {
    "id": 3001016,
    "text": null
  },
  {
    "id": 3001017,
    "text": null
  },
  {
    "id": 3001018,
    "text": null
  },
  {
    "id": 3001019,
    "text": null
  },
  {
    "id": 3001020,
    "text": null
  },
  {
    "id": 3001021,
    "text": null
  },
  {
    "id": 3001022,
    "text": null
  },
  {
    "id": 3001023,
    "text": null
  },
  {
    "id": 3001024,
    "text": null
  },
  {
    "id": 3001025,
    "text": null
  },
  {
    "id": 3001026,
    "text": null
  },
  {
    "id": 3001027,
    "text": null
  }
]